{
  "contacts": {
    "Phone": "+39 080 697 0910",
    "Address": "S.S. 100 Km.18 c/o \"il Baricentro\"<br>Lotto 5 Modulo n° 14-15<br>70010 Casamassima BA",
    "Mail": "<b>Vendite</b><br>davidedicarne@gmail.com<br><b>Segreteria</b><br>marcello.dicarne@gmail.com"
  },
  "map": {
    "coordinates": [
      16.917119,
      40.979592
    ],
    "zoom": 14
  },
  "gallery": [
    "/gallery1.jpg",
    "/gallery2.png",
    "/gallery3.jpg"
  ],
  "name": "Di Carne Show Room",
  "primaryColor": "#2b4982",
  "secondaryColor": "#00000"
}
